aws_2fa/__init__.py
aws_2fa/cli.py
aws_2fa-0.1.4.dist-info/METADATA
aws_2fa-0.1.4.dist-info/WHEEL
aws_2fa-0.1.4.dist-info/entry_points.txt
aws_2fa-0.1.4.dist-info/top_level.txt
aws_2fa-0.1.4.dist-info/RECORD
